shobdo/__init__.py
shobdo/core.py
shobdo/models.py
shobdo/utils.py
shobdo/data/dictionary.db
shobdo/data/embeddings.npy
shobdo/data/word_index.json
shobdo-0.1.0.dist-info/METADATA
shobdo-0.1.0.dist-info/WHEEL
shobdo-0.1.0.dist-info/RECORD
