Metadata-Version: 2.4
Name: shobdo
Version: 0.1.0
Summary: A modern, high-performance Python library for Bengali dictionary operations.
Author-email: Shobdo Team <info@example.com>
Requires-Python: >=3.9
Requires-Dist: pydantic>=2.0.0
